E_Sic/__init__.py
E_Sic/pedidos_respostas/__init__.py
E_Sic/pedidos_respostas/conts.py
E_Sic/pedidos_respostas/exceptions.py
E_Sic/pedidos_respostas/parser.py
E_Sic/pedidos_respostas/search.py
E_Sic/pedidos_respostas/types.py
E_Sic-2020.2.15.dist-info/LICENSE
E_Sic-2020.2.15.dist-info/METADATA
E_Sic-2020.2.15.dist-info/WHEEL
E_Sic-2020.2.15.dist-info/top_level.txt
E_Sic-2020.2.15.dist-info/RECORD
