Metadata-Version: 2.1
Name: E-Sic
Version: 2020.2.15
Summary: Pacote para automatização de coletas no portal E-Sic, você pode obter os dados sobre as perguntas, respostas e até mesmo baixar os arquivos anexados.
Home-page: https://github.com/riquedev/E-Sic-Scraper
Author: Henrique da Silva Santos
License: UNKNOWN
Project-URL: Bug Reports, https://github.com/riquedev/E-Sic-Scraper/issues
Project-URL: Source, https://github.com/riquedev/E-Sic-Scraper
Keywords: dados-abertos dadosgovbr scraper e-sic brasil perguntas-e-respostas
Platform: UNKNOWN
Requires-Python: >=3.6
Requires-Dist: aiofile (==1.5.2)
Requires-Dist: aiofiles (==0.4.0)
Requires-Dist: aiohttp (==3.6.2)
Requires-Dist: appdirs (==1.4.3)
Requires-Dist: async-timeout (==3.0.1)
Requires-Dist: asyncio (==3.4.3)
Requires-Dist: attrs (==19.3.0)
Requires-Dist: beautifulsoup4 (==4.8.2)
Requires-Dist: bs4 (==0.0.1)
Requires-Dist: certifi (==2019.11.28)
Requires-Dist: chardet (==3.0.4)
Requires-Dist: cssselect (==1.1.0)
Requires-Dist: fake-useragent (==0.1.11)
Requires-Dist: idna (==2.8)
Requires-Dist: idna-ssl (==1.1.0)
Requires-Dist: lxml (==4.5.0)
Requires-Dist: multidict (==4.7.4)
Requires-Dist: parse (==1.14.0)
Requires-Dist: pyee (==7.0.1)
Requires-Dist: pyppeteer (==0.0.25)
Requires-Dist: pyquery (==1.4.1)
Requires-Dist: requests (==2.22.0)
Requires-Dist: requests-html
Requires-Dist: six (==1.14.0)
Requires-Dist: soupsieve (==1.9.5)
Requires-Dist: tqdm (==4.42.1)
Requires-Dist: typing-extensions (==3.7.4.1)
Requires-Dist: urllib3 (==1.25.8)
Requires-Dist: w3lib (==1.21.0)
Requires-Dist: websockets
Requires-Dist: yarl
Requires-Dist: codecov
